{
  "id": "wand-of-web-dmg",
  "name": "Жезл паутины",
  "nameEn": "Wand of Web",
  "description": "Этот жезл содержит 7 зарядов. Держа его, вы можете действием потратить 1 заряд для сотворения заклинания «Паутина» (Сл спасброска 15) с помощью жезла.\n\nЖезл восстанавливает {@roll 1d6+1} потраченных зарядов ежедневно на заре. Если вы потратите последний заряд, бросьте {@roll 1d20}. Если выпадет 1, жезл рассыпается в прах и уничтожается.",
  "type": "equipment",
  "quantity": 1,
  "weight": 1,
  "cost": "",
  "rarity": "uncommon",
  "equipped": false,
  "equipmentCategory": "wand",
  "baseArmorAC": 0,
  "maxDexBonus": null,
  "stealthDisadvantage": false,
  "strengthRequirement": 0,
  "sourceKey": "dmg",
  "isSRD": true,
  "isReadOnly": true,
  "isMagical": true,
  "magicAttunement": "required",
  "typeLabel": "Снаряжение"
}
